hcilib/__init__.py
hcilib/__main__.py
hcilib/base/__init__.py
hcilib/base/calc.py
hcilib/base/combase.py
hcilib/base/conf.py
hcilib/base/tools.py
hcilib/export/__init__.py
hcilib/export/comsys.py
hcilib/export/comwf.py
hcilib/recovery/__init__.py
hcilib/recovery/recovery.py
hcilib/version/__init__.py
hciexport-0.4.0.dist-info/METADATA
hciexport-0.4.0.dist-info/WHEEL
hciexport-0.4.0.dist-info/entry_points.txt
hciexport-0.4.0.dist-info/top_level.txt
hciexport-0.4.0.dist-info/RECORD
