Metadata-Version: 2.1
Name: hciexport
Version: 0.4.0
Summary: HCI configuration and workflow export; index backup/restore
Project-URL: Homepage, https://hciexport.readthedocs.io/en/latest/
Project-URL: Issues, https://gitlab.com/simont3/hciexport/issues
Classifier: Programming Language :: Python :: 3.8
Classifier: License :: OSI Approved :: MIT License
Classifier: Operating System :: OS Independent
Classifier: Development Status :: 5 - Production/Stable
Classifier: Environment :: Console
Classifier: Intended Audience :: System Administrators
Classifier: Topic :: System :: Systems Administration
Classifier: Topic :: Utilities
Requires-Python: >=3.8
Requires-Dist: httpx
